MANIFEST.in
README.md
setup.cfg
setup.py
django_futon.egg-info/PKG-INFO
django_futon.egg-info/SOURCES.txt
django_futon.egg-info/dependency_links.txt
django_futon.egg-info/not-zip-safe
django_futon.egg-info/requires.txt
django_futon.egg-info/top_level.txt
futon/__init__.py
futon/admin.py
futon/credentials.py
futon/models.py
futon/only_one.py
futon/requests.py
futon/resource.py
futon/tasks.py
futon/views.py
futon/management/__init__.py
futon/management/commands/__init__.py
futon/management/commands/init_sync_site_schedule.py
futon/management/commands/revoke_tokens.py
futon/management/commands/sync_sites.py
futon/migrations/0001_initial.py
futon/migrations/__init__.py
futon/tests/__init__.py
futon/tests/test_requests.py
futon/tests/test_resource.py
futon/tests/test_tasks.py