Metadata-Version: 1.1
Name: django-futon
Version: 0.1.5
Summary: A lightweight application for synchronising Django models between sites using RESTful APIs.
Home-page: https://github.com/uptick/django-futon
Author: Uptick
Author-email: dev@uptickhq.com
License: BSD
Platform: UNKNOWN
Classifier: Development Status :: 3 - Alpha
Classifier: Framework :: Django
Classifier: Intended Audience :: Developers
Classifier: License :: OSI Approved :: BSD License
Classifier: Natural Language :: English
Classifier: Operating System :: OS Independent
Classifier: Programming Language :: Python
Classifier: Programming Language :: Python :: 3
